Metadata-Version: 2.1
Name: hyperkv
Version: 0.1.1
Summary: Reads from Hyper-V KV on a Linux guest
Home-page: https://github.com/phistrom/hyperkv
Author: Phillip Stromberg
Author-email: phillip@strombergs.com
License: MIT
Platform: UNKNOWN
Classifier: Development Status :: 4 - Beta
Classifier: Intended Audience :: Developers
Classifier: Natural Language :: English
Classifier: License :: OSI Approved :: MIT License
Classifier: Programming Language :: Python
Classifier: Programming Language :: Python :: 3
